{
  "article_file": "Epigenetika_4_Inzuln_aATP_ako_Biologick_polovodi.json",
  "article_title": "Epigenetika #4 Inzulín a ATP ako Biologický polovodič",
  "article_url": "https://jaroslavlachky.sk/epigenetika-4-inzulin-a-atp-ako-biologicky-polovodic/",
  "article_date": "2022-11-27T00:00:00+01:00",
  "reference_section": "https://cs.m.wikipedia.org/wiki/Epigenetika\n\n\n\nhttps://www.wikiskripta.eu/w/Epigenetika\n\n\n\nhttps://www.ncbi.nlm.nih.gov/pmc/articles/PMC149470/\n\n\n\nhttps://www.nature.com/articles/359644a0\n\n\n\nhttps://www.ncbi.nlm.nih.gov/pmc/articles/PMC14759/\n\n\n\nhttps://www.molbiolcell.org/doi/abs/10.1091/mbc.4.5.523\n\n\n\nhttps://www.wikiskripta.eu/w/Inzulin\n\n\n\nhttp://www.quantum.physics.sk/rcqi/docs/popular/quark_maxwell_demon.pdf\n\n\n\nhttps://www.wikiskripta.eu/w/Receptorem_zprost%C5%99edkovan%C3%A1_endocyt%C3%B3z...",
  "total_sources": 9,
  "sources_by_category": {
    "academic": [
      "https://www.ncbi.nlm.nih.gov/pmc/articles/PMC14759/",
      "https://www.nature.com/articles/359644a0",
      "https://www.ncbi.nlm.nih.gov/pmc/articles/PMC149470/"
    ],
    "news": [],
    "government": [],
    "social_media": [],
    "blog": [],
    "other": [
      "https://cs.m.wikipedia.org/wiki/Epigenetika",
      "https://www.wikiskripta.eu/w/Receptorem_zprost",
      "http://www.quantum.physics.sk/rcqi/docs/popular/quark_maxwell_demon.pdf",
      "https://www.wikiskripta.eu/w/Epigenetika",
      "https://www.wikiskripta.eu/w/Inzulin",
      "https://www.molbiolcell.org/doi/abs/10.1091/mbc.4.5.523"
    ]
  },
  "all_sources": [
    "https://cs.m.wikipedia.org/wiki/Epigenetika",
    "https://www.wikiskripta.eu/w/Receptorem_zprost",
    "https://www.ncbi.nlm.nih.gov/pmc/articles/PMC14759/",
    "http://www.quantum.physics.sk/rcqi/docs/popular/quark_maxwell_demon.pdf",
    "https://www.wikiskripta.eu/w/Epigenetika",
    "https://www.wikiskripta.eu/w/Inzulin",
    "https://www.molbiolcell.org/doi/abs/10.1091/mbc.4.5.523",
    "https://www.nature.com/articles/359644a0",
    "https://www.ncbi.nlm.nih.gov/pmc/articles/PMC149470/"
  ],
  "extracted_at": "2025-07-15T15:55:29.463755"
}